azure/mgmt/hybridkubernetes/__init__.py
azure/mgmt/hybridkubernetes/_configuration.py
azure/mgmt/hybridkubernetes/_connected_kubernetes_client.py
azure/mgmt/hybridkubernetes/_version.py
azure/mgmt/hybridkubernetes/aio/__init__.py
azure/mgmt/hybridkubernetes/aio/_configuration.py
azure/mgmt/hybridkubernetes/aio/_connected_kubernetes_client.py
azure/mgmt/hybridkubernetes/aio/operations/__init__.py
azure/mgmt/hybridkubernetes/aio/operations/_connected_cluster_operations.py
azure/mgmt/hybridkubernetes/aio/operations/_operations.py
azure/mgmt/hybridkubernetes/models/__init__.py
azure/mgmt/hybridkubernetes/models/_connected_kubernetes_client_enums.py
azure/mgmt/hybridkubernetes/models/_models.py
azure/mgmt/hybridkubernetes/models/_models_py3.py
azure/mgmt/hybridkubernetes/operations/__init__.py
azure/mgmt/hybridkubernetes/operations/_connected_cluster_operations.py
azure/mgmt/hybridkubernetes/operations/_operations.py
azure_mgmt_hybridkubernetes-1.1.0.dist-info/METADATA
azure_mgmt_hybridkubernetes-1.1.0.dist-info/WHEEL
azure_mgmt_hybridkubernetes-1.1.0.dist-info/top_level.txt
azure_mgmt_hybridkubernetes-1.1.0.dist-info/RECORD
